{
  "particleCount": 1000,
  "particleSize": 4.4,
  "fadeSpeed": 0.0074,
  "maxTravelDistance": 500,
  "travelSpeed": 0.1,
  "momentum": 0.945,
  "friction": 0,
  "connectionDistance": 110,
  "lineThickness": 1.3,
  "connectionFadeSpeed": 0.042,
  "attractionStrength": 2,
  "attractionDistance": 80,
  "attractionMomentum": 1,
  "repulsionStrength": 0,
  "maxIterations": 100,
  "zoom": 23,
  "seahorseX": -0.745,
  "seahorseY": 0.1,
  "fullMatrixMode": false,
  "colorfulMode": false,
  "persistentConnections": false,
  "particlesOnTop": true,
  "particleColor": "#ff2600",
  "particleOpacity": 100,
  "lineColor": "#feffff",
  "lineOpacity": 100,
  "dotColor": "#00ffff",
  "dotOpacity": 100,
  "pattern": "grid",
  "patternScale": 3.4,
  "patternDistance": 1,
  "glowIntensity": 0.5,
  "minOpacity": 0.1,
  "maxOpacity": 0.8,
  "particleSpawnRate": 10,
  "minParticleLife": 0.5,
  "maxParticleLife": 2,
  "fadeInDuration": 0.2,
  "fadeOutDuration": 0.3,
  "timestamp": "2024-12-17T05:54:44.374Z",
  "name": "Red Grid 2"
}